{"v":"5.10.0","fr":30,"ip":0,"op":120,"w":1920,"h":1080,"nm":"front raises","ddd":0,"assets":[],"layers":[{"ddd":0,"ind":1,"ty":4,"nm":"hand l Outlines","parent":2,"sr":1,"ks":{"o":{"a":0,"k":100,"ix":11},"r":{"a":1,"k":[{"i":{"x":[0.353],"y":[1]},"o":{"x":[0.333],"y":[0]},"t":0,"s":[-28]},{"i":{"x":[0.667],"y":[1]},"o":{"x":[0.653],"y":[0]},"t":30,"s":[-22]},{"t":60,"s":[-28]}],"ix":10},"p":{"a":0,"k":[25.607,163.752,0],"ix":2,"l":2},"a":{"a":0,"k":[182.997,24.588,0],"ix":1,"l":2},"s":{"a":0,"k":[100,100,100],"ix":6,"l":2}},"ao":0,"shapes":[{"ty":"gr","it":[{"ind":0,"ty":"sh","ix":1,"ks":{"a":0,"k":{"i":[[-2.082,6.375],[6.375,2.082],[2.082,-6.375],[-6.374,-2.082]],"o":[[2.083,-6.375],[-6.375,-2.083],[-2.082,6.375],[6.375,2.083]],"v":[[11.542,3.77],[3.77,-11.543],[-11.543,-3.77],[-3.771,11.543]],"c":true},"ix":2},"nm":"Path 1","mn":"ADBE Vector Shape - Group","hd":false},{"ty":"fl","c":{"a":0,"k":[0.800000059838,0.800000059838,0.800000059838,1],"ix":4},"o":{"a":0,"k":100,"ix":5},"r":1,"bm":0,"nm":"Fill 1","mn":"ADBE Vector Graphic - Fill","hd":false},{"ty":"tr","p":{"a":0,"k":[80.198,144.979],"ix":2},"a":{"a":0,"k":[0,0],"ix":1},"s":{"a":0,"k":[100,100],"ix":3},"r":{"a":0,"k":0,"ix":6},"o":{"a":0,"k":100,"ix":7},"sk":{"a":0,"k":0,"ix":4},"sa":{"a":0,"k":0,"ix":5},"nm":"Transform"}],"nm":"Group 1","np":2,"cix":2,"bm":0,"ix":1,"mn":"ADBE Vector Group","hd":false},{"ty":"gr","it":[{"ind":0,"ty":"sh","ix":1,"ks":{"a":0,"k":{"i":[[-3.527,10.797],[10.798,3.527],[3.527,-10.797],[-10.797,-3.527]],"o":[[3.527,-10.798],[-10.797,-3.526],[-3.526,10.798],[10.798,3.526]],"v":[[19.551,6.386],[6.385,-19.551],[-19.552,-6.386],[-6.386,19.551]],"c":true},"ix":2},"nm":"Path 1","mn":"ADBE Vector Shape - Group","hd":false},{"ty":"fl","c":{"a":0,"k":[0.686274509804,0.686274509804,0.686274509804,1],"ix":4},"o":{"a":0,"k":100,"ix":5},"r":1,"bm":0,"nm":"Fill 1","mn":"ADBE Vector Graphic - Fill","hd":false},{"ty":"tr","p":{"a":0,"k":[80.198,144.979],"ix":2},"a":{"a":0,"k":[0,0],"ix":1},"s":{"a":0,"k":[100,100],"ix":3},"r":{"a":0,"k":0,"ix":6},"o":{"a":0,"k":100,"ix":7},"sk":{"a":0,"k":0,"ix":4},"sa":{"a":0,"k":0,"ix":5},"nm":"Transform"}],"nm":"Group 2","np":2,"cix":2,"bm":0,"ix":2,"mn":"ADBE Vector Group","hd":false},{"ty":"gr","it":[{"ind":0,"ty":"sh","ix":1,"ks":{"a":0,"k":{"i":[[-10.329,31.621],[31.621,10.329],[10.329,-31.621],[-31.621,-10.329]],"o":[[10.328,-31.622],[-31.622,-10.329],[-10.328,31.622],[31.622,10.328]],"v":[[57.256,18.701],[18.702,-57.256],[-57.256,-18.701],[-18.702,57.256]],"c":true},"ix":2},"nm":"Path 1","mn":"ADBE Vector Shape - Group","hd":false},{"ty":"fl","c":{"a":0,"k":[0.537254901961,0.537254901961,0.537254901961,1],"ix":4},"o":{"a":0,"k":100,"ix":5},"r":1,"bm":0,"nm":"Fill 1","mn":"ADBE Vector Graphic - Fill","hd":false},{"ty":"tr","p":{"a":0,"k":[80.197,144.979],"ix":2},"a":{"a":0,"k":[0,0],"ix":1},"s":{"a":0,"k":[100,100],"ix":3},"r":{"a":0,"k":0,"ix":6},"o":{"a":0,"k":100,"ix":7},"sk":{"a":0,"k":0,"ix":4},"sa":{"a":0,"k":0,"ix":5},"nm":"Transform"}],"nm":"Group 3","np":2,"cix":2,"bm":0,"ix":3,"mn":"ADBE Vector Group","hd":false},{"ty":"gr","it":[{"ind":0,"ty":"sh","ix":1,"ks":{"a":0,"k":{"i":[[-12.218,37.406],[37.406,12.218],[12.218,-37.406],[-37.406,-12.218]],"o":[[12.218,-37.406],[-37.406,-12.217],[-12.218,37.406],[37.406,12.218]],"v":[[67.73,22.122],[22.122,-67.73],[-67.73,-22.123],[-22.123,67.729]],"c":true},"ix":2},"nm":"Path 1","mn":"ADBE Vector Shape - Group","hd":false},{"ty":"fl","c":{"a":0,"k":[0.686274509804,0.686274509804,0.686274509804,1],"ix":4},"o":{"a":0,"k":100,"ix":5},"r":1,"bm":0,"nm":"Fill 1","mn":"ADBE Vector Graphic - Fill","hd":false},{"ty":"tr","p":{"a":0,"k":[80.197,144.98],"ix":2},"a":{"a":0,"k":[0,0],"ix":1},"s":{"a":0,"k":[100,100],"ix":3},"r":{"a":0,"k":0,"ix":6},"o":{"a":0,"k":100,"ix":7},"sk":{"a":0,"k":0,"ix":4},"sa":{"a":0,"k":0,"ix":5},"nm":"Transform"}],"nm":"Group 4","np":2,"cix":2,"bm":0,"ix":4,"mn":"ADBE Vector Group","hd":false},{"ty":"gr","it":[{"ind":0,"ty":"sh","ix":1,"ks":{"a":0,"k":{"i":[[8.573,-9.682],[0,0],[8.161,7.788],[-6.24,8.061],[0,0],[-10.055,-8.981]],"o":[[0,0],[-7.478,8.446],[-7.375,-7.038],[0,0],[8.411,-10.536],[9.644,8.615]],"v":[[50.163,-24.134],[-21.863,57.21],[-50.499,58.414],[-52.496,31.841],[14.223,-54.357],[48.224,-57.221]],"c":true},"ix":2},"nm":"Path 1","mn":"ADBE Vector Shape - Group","hd":false},{"ty":"fl","c":{"a":0,"k":[0.380392186782,0.61568627451,0.807843197093,1],"ix":4},"o":{"a":0,"k":100,"ix":5},"r":1,"bm":0,"nm":"Fill 1","mn":"ADBE Vector Graphic - Fill","hd":false},{"ty":"tr","p":{"a":0,"k":[149.009,66.452],"ix":2},"a":{"a":0,"k":[0,0],"ix":1},"s":{"a":0,"k":[100,100],"ix":3},"r":{"a":0,"k":0,"ix":6},"o":{"a":0,"k":100,"ix":7},"sk":{"a":0,"k":0,"ix":4},"sa":{"a":0,"k":0,"ix":5},"nm":"Transform"}],"nm":"Group 5","np":2,"cix":2,"bm":0,"ix":5,"mn":"ADBE Vector Group","hd":false}],"ip":0,"op":120,"st":0,"ct":1,"bm":0},{"ddd":0,"ind":2,"ty":4,"nm":"hand u Outlines","sr":1,"ks":{"o":{"a":0,"k":100,"ix":11},"r":{"a":1,"k":[{"i":{"x":[0.353],"y":[1]},"o":{"x":[0.333],"y":[0]},"t":0,"s":[-12]},{"i":{"x":[0.667],"y":[1]},"o":{"x":[0.653],"y":[0]},"t":30,"s":[75]},{"t":60,"s":[-12]}],"ix":10},"p":{"a":0,"k":[1024.484,268.86,0],"ix":2,"l":2},"a":{"a":0,"k":[60.884,22.834,0],"ix":1,"l":2},"s":{"a":0,"k":[100,100,100],"ix":6,"l":2}},"ao":0,"shapes":[{"ty":"gr","it":[{"ind":0,"ty":"sh","ix":1,"ks":{"a":0,"k":{"i":[[3.75,-16.604],[0,0],[-11.853,-3.481],[-3.868,12.456],[0,0],[-0.244,1.64],[24.162,6.097]],"o":[[0,0],[-2.398,12.118],[12.514,3.675],[0,0],[0.509,-1.578],[1.41,-9.501],[-16.505,-4.164]],"v":[[-16.389,-67.195],[-42.236,63.363],[-25.542,90.909],[3.988,75.081],[39.497,-39.262],[40.634,-44.093],[20.473,-90.42]],"c":true},"ix":2},"nm":"Path 1","mn":"ADBE Vector Shape - Group","hd":false},{"ty":"fl","c":{"a":0,"k":[0.380392186782,0.61568627451,0.807843197093,1],"ix":4},"o":{"a":0,"k":100,"ix":5},"r":1,"bm":0,"nm":"Fill 1","mn":"ADBE Vector Graphic - Fill","hd":false},{"ty":"tr","p":{"a":0,"k":[44.884,94.834],"ix":2},"a":{"a":0,"k":[0,0],"ix":1},"s":{"a":0,"k":[100,100],"ix":3},"r":{"a":0,"k":0,"ix":6},"o":{"a":0,"k":100,"ix":7},"sk":{"a":0,"k":0,"ix":4},"sa":{"a":0,"k":0,"ix":5},"nm":"Transform"}],"nm":"Group 1","np":2,"cix":2,"bm":0,"ix":1,"mn":"ADBE Vector Group","hd":false}],"ip":0,"op":120,"st":0,"ct":1,"bm":0},{"ddd":0,"ind":3,"ty":4,"nm":"body Outlines","sr":1,"ks":{"o":{"a":0,"k":100,"ix":11},"r":{"a":0,"k":0,"ix":10},"p":{"a":0,"k":[1014.748,324.405,0],"ix":2,"l":2},"a":{"a":0,"k":[101.309,305.825,0],"ix":1,"l":2},"s":{"a":0,"k":[100,100,100],"ix":6,"l":2}},"ao":0,"shapes":[{"ty":"gr","it":[{"ind":0,"ty":"sh","ix":1,"ks":{"a":0,"k":{"i":[[27.863,3.054],[2.076,0.541],[0,0],[-0.426,2.716],[-37.398,-40.956]],"o":[[-2.182,-0.228],[-28.656,-7.42],[0,0],[2.181,-14.139],[41.317,45.264]],"v":[[-12.897,50.725],[-19.308,49.566],[-43.299,5.486],[-42.737,1.035],[6.647,-12.824]],"c":true},"ix":2},"nm":"Path 1","mn":"ADBE Vector Shape - Group","hd":false},{"ty":"fl","c":{"a":0,"k":[0,0,0,1],"ix":4},"o":{"a":0,"k":100,"ix":5},"r":1,"bm":0,"nm":"Fill 1","mn":"ADBE Vector Graphic - Fill","hd":false},{"ty":"tr","p":{"a":0,"k":[154.403,54.03],"ix":2},"a":{"a":0,"k":[0,0],"ix":1},"s":{"a":0,"k":[100,100],"ix":3},"r":{"a":0,"k":0,"ix":6},"o":{"a":0,"k":100,"ix":7},"sk":{"a":0,"k":0,"ix":4},"sa":{"a":0,"k":0,"ix":5},"nm":"Transform"}],"nm":"Group 1","np":2,"cix":2,"bm":0,"ix":1,"mn":"ADBE Vector Group","hd":false},{"ty":"gr","it":[{"ind":0,"ty":"sh","ix":1,"ks":{"a":0,"k":{"i":[[2.408,-8.538],[4.729,-5.642],[0,0],[0,0],[0.367,-0.168],[6.814,7.648],[0.482,6.103],[2.817,8.929],[5.666,-5.508],[1.656,7.834],[0.049,0.298],[11.861,0.167],[0,0],[-34.7,7.964],[-19.876,-11.308],[0,0],[-28.657,-7.42],[-2.182,-0.228]],"o":[[-2.008,7.081],[-5.541,6.61],[0,0],[-0.368,0.199],[-9.328,4.244],[-3.32,-3.739],[3.646,-6.395],[-3.718,-11.773],[1.367,-8.838],[-0.059,-0.278],[-1.795,-11.721],[-6.897,-0.095],[0,0],[10.137,-2.324],[-0.426,2.716],[0,0],[2.076,0.541],[1.353,14.805]],"v":[[54.693,33.261],[44.625,52.648],[35.222,60.216],[35.207,60.114],[34.097,60.659],[6.911,54.542],[0.241,39.784],[5.617,20.448],[-12.352,13.575],[-21.271,-12.586],[-21.428,-13.453],[-44.719,-34.299],[-56.466,-35.188],[-25.234,-61.141],[28.741,-53.594],[28.178,-49.143],[52.17,-5.063],[58.581,-3.904]],"c":true},"ix":2},"nm":"Path 1","mn":"ADBE Vector Shape - Group","hd":false},{"ty":"fl","c":{"a":0,"k":[0,0,0,1],"ix":4},"o":{"a":0,"k":100,"ix":5},"r":1,"bm":0,"nm":"Fill 1","mn":"ADBE Vector Graphic - Fill","hd":false},{"ty":"tr","p":{"a":0,"k":[90.886,104.558],"ix":2},"a":{"a":0,"k":[0,0],"ix":1},"s":{"a":0,"k":[100,100],"ix":3},"r":{"a":0,"k":0,"ix":6},"o":{"a":0,"k":100,"ix":7},"sk":{"a":0,"k":0,"ix":4},"sa":{"a":0,"k":0,"ix":5},"nm":"Transform"}],"nm":"Group 2","np":2,"cix":2,"bm":0,"ix":2,"mn":"ADBE Vector Group","hd":false},{"ty":"gr","it":[{"ind":0,"ty":"sh","ix":1,"ks":{"a":0,"k":{"i":[[-2.768,28.906],[0,0],[-1.031,-20.218],[5.447,-16.682],[0,0],[27.685,0],[1.82,33.986]],"o":[[0,0],[17.328,16.806],[0.906,17.776],[0,0],[-8.594,26.316],[-34.034,0],[-2.258,-42.152]],"v":[[-66.575,-85.775],[44.576,-86.301],[68.437,-25.492],[61.311,26.749],[56.273,42.18],[-4.55,86.301],[-64.357,25.666]],"c":true},"ix":2},"nm":"Path 1","mn":"ADBE Vector Shape - Group","hd":false},{"ty":"fl","c":{"a":0,"k":[0,0,0,1],"ix":4},"o":{"a":0,"k":100,"ix":5},"r":1,"bm":0,"nm":"Fill 1","mn":"ADBE Vector Graphic - Fill","hd":false},{"ty":"tr","p":{"a":0,"k":[98.195,525.099],"ix":2},"a":{"a":0,"k":[0,0],"ix":1},"s":{"a":0,"k":[100,100],"ix":3},"r":{"a":0,"k":0,"ix":6},"o":{"a":0,"k":100,"ix":7},"sk":{"a":0,"k":0,"ix":4},"sa":{"a":0,"k":0,"ix":5},"nm":"Transform"}],"nm":"Group 3","np":2,"cix":2,"bm":0,"ix":3,"mn":"ADBE Vector Group","hd":false},{"ty":"gr","it":[{"ind":0,"ty":"sh","ix":1,"ks":{"a":0,"k":{"i":[[6.879,-25.4],[0,0],[0,0],[1.145,9.099],[7.672,10.748],[-20.967,19.242],[-12.317,10.497],[-1.729,-1.125],[-0.009,0],[-3.199,-3.934],[-0.457,-11.183]],"o":[[-9.139,19.815],[0,0],[0.086,-15.009],[-1.648,-13.103],[-9.195,-12.882],[26.567,-24.389],[23.785,-20.276],[0.011,0],[4.229,2.061],[7.061,8.684],[0.471,11.511]],"v":[[68.876,8.235],[59.298,102.998],[-46.793,102.998],[-48.928,67.157],[-62.984,30.728],[-55.502,-17.453],[6.41,-82.722],[53.418,-88.696],[53.438,-88.686],[64.66,-79.246],[75.998,-48.516]],"c":true},"ix":2},"nm":"Path 1","mn":"ADBE Vector Shape - Group","hd":false},{"ty":"fl","c":{"a":0,"k":[0.329411764706,0.552941176471,0.776470648074,1],"ix":4},"o":{"a":0,"k":100,"ix":5},"r":1,"bm":0,"nm":"Fill 1","mn":"ADBE Vector Graphic - Fill","hd":false},{"ty":"tr","p":{"a":0,"k":[76.719,293.244],"ix":2},"a":{"a":0,"k":[0,0],"ix":1},"s":{"a":0,"k":[100,100],"ix":3},"r":{"a":0,"k":0,"ix":6},"o":{"a":0,"k":100,"ix":7},"sk":{"a":0,"k":0,"ix":4},"sa":{"a":0,"k":0,"ix":5},"nm":"Transform"}],"nm":"Group 4","np":2,"cix":2,"bm":0,"ix":4,"mn":"ADBE Vector Group","hd":false},{"ty":"gr","it":[{"ind":0,"ty":"sh","ix":1,"ks":{"a":0,"k":{"i":[[0,0],[0,0],[-11.963,-16.778],[0,0]],"o":[[0,0],[0,0],[0,0],[0,0]],"v":[[-57.009,-46.225],[51.987,-46.225],[57.009,46.225],[-54.141,46.225]],"c":true},"ix":2},"nm":"Path 1","mn":"ADBE Vector Shape - Group","hd":false},{"ty":"fl","c":{"a":0,"k":[1,0.752941236309,0.701960784314,1],"ix":4},"o":{"a":0,"k":100,"ix":5},"r":1,"bm":0,"nm":"Fill 1","mn":"ADBE Vector Graphic - Fill","hd":false},{"ty":"tr","p":{"a":0,"k":[85.762,392.573],"ix":2},"a":{"a":0,"k":[0,0],"ix":1},"s":{"a":0,"k":[100,100],"ix":3},"r":{"a":0,"k":0,"ix":6},"o":{"a":0,"k":100,"ix":7},"sk":{"a":0,"k":0,"ix":4},"sa":{"a":0,"k":0,"ix":5},"nm":"Transform"}],"nm":"Group 5","np":2,"cix":2,"bm":0,"ix":5,"mn":"ADBE Vector Group","hd":false},{"ty":"gr","it":[{"ind":0,"ty":"sh","ix":1,"ks":{"a":0,"k":{"i":[[0,0],[0,0],[0,0],[0,0]],"o":[[0,0],[0,0],[0,0],[0,0]],"v":[[19.689,-24.752],[17.467,26.366],[-19.689,24.752],[-17.467,-26.366]],"c":true},"ix":2},"nm":"Path 1","mn":"ADBE Vector Shape - Group","hd":false},{"ind":1,"ty":"sh","ix":2,"ks":{"a":0,"k":{"i":[[0,0],[-28.656,-7.421],[-2.181,-0.229],[1.092,4.102],[12.08,6.874]],"o":[[0,0],[2.076,0.54],[-0.366,-4.051],[-5.044,-18.968],[-0.427,2.716]],"v":[[-12.868,-20.395],[11.122,23.686],[17.534,24.845],[15.394,12.577],[-12.305,-24.845]],"c":true},"ix":2},"nm":"Path 2","mn":"ADBE Vector Shape - Group","hd":false},{"ty":"mm","mm":4,"nm":"Merge Paths 1","mn":"ADBE Vector Filter - Merge","hd":false},{"ty":"fl","c":{"a":0,"k":[0.5,0.5,0.5,1],"ix":4},"o":{"a":0,"k":100,"ix":5},"r":1,"bm":0,"nm":"Fill 1","mn":"ADBE Vector Graphic - Fill","hd":false},{"ty":"tr","p":{"a":0,"k":[131.933,75.809],"ix":2},"a":{"a":0,"k":[0,0],"ix":1},"s":{"a":0,"k":[100,100],"ix":3},"r":{"a":0,"k":0,"ix":6},"o":{"a":0,"k":100,"ix":7},"sk":{"a":0,"k":0,"ix":4},"sa":{"a":0,"k":0,"ix":5},"nm":"Transform"}],"nm":"Group 6","np":4,"cix":2,"bm":0,"ix":6,"mn":"ADBE Vector Group","hd":false},{"ty":"gr","it":[{"ind":0,"ty":"sh","ix":1,"ks":{"a":0,"k":{"i":[[2.842,35.702],[-4.314,35.369],[35.344,-3.232],[6.167,-13.561],[2.423,-19.941],[4.422,-4.496],[-0.518,-1.593],[-2.986,-3.574],[2.632,-3.697],[-0.132,-1.291],[-0.662,-3.42],[-4.851,-5.808],[-6.81,-2.722]],"o":[[2.464,-16.526],[4.789,-39.247],[-14.265,1.305],[-6.184,13.596],[-0.673,5.538],[-3.287,3.343],[2.278,7.013],[1.115,1.338],[-1.795,2.521],[0.409,3.985],[1.074,5.545],[3.333,3.992],[0,0]],"v":[[34.59,27.948],[61.277,-8.766],[-18.465,-60.418],[-42.989,-46.868],[-45.458,-12.782],[-59.332,3.755],[-65.548,9.977],[-55.724,18.92],[-54.749,26.725],[-52.876,32.923],[-50.518,38.901],[-50.958,55.535],[-11.628,61.321]],"c":true},"ix":2},"nm":"Path 1","mn":"ADBE Vector Shape - Group","hd":false},{"ty":"fl","c":{"a":0,"k":[1,0.752941236309,0.701960784314,1],"ix":4},"o":{"a":0,"k":100,"ix":5},"r":1,"bm":0,"nm":"Fill 1","mn":"ADBE Vector Graphic - Fill","hd":false},{"ty":"tr","p":{"a":0,"k":[71.034,125.855],"ix":2},"a":{"a":0,"k":[0,0],"ix":1},"s":{"a":0,"k":[100,100],"ix":3},"r":{"a":0,"k":0,"ix":6},"o":{"a":0,"k":100,"ix":7},"sk":{"a":0,"k":0,"ix":4},"sa":{"a":0,"k":0,"ix":5},"nm":"Transform"}],"nm":"Group 7","np":2,"cix":2,"bm":0,"ix":7,"mn":"ADBE Vector Group","hd":false},{"ty":"gr","it":[{"ind":0,"ty":"sh","ix":1,"ks":{"a":0,"k":{"i":[[0,0],[0,0],[14.936,25.715],[0,0]],"o":[[0,0],[8.707,-34.665],[0,0],[0,0]],"v":[[35.351,36.831],[-22.482,54.89],[-35.351,-29.675],[23.545,-54.89]],"c":true},"ix":2},"nm":"Path 1","mn":"ADBE Vector Shape - Group","hd":false},{"ty":"fl","c":{"a":0,"k":[1,0.752941236309,0.701960784314,1],"ix":4},"o":{"a":0,"k":100,"ix":5},"r":1,"bm":0,"nm":"Fill 1","mn":"ADBE Vector Graphic - Fill","hd":false},{"ty":"tr","p":{"a":0,"k":[91.533,195.72],"ix":2},"a":{"a":0,"k":[0,0],"ix":1},"s":{"a":0,"k":[100,100],"ix":3},"r":{"a":0,"k":0,"ix":6},"o":{"a":0,"k":100,"ix":7},"sk":{"a":0,"k":0,"ix":4},"sa":{"a":0,"k":0,"ix":5},"nm":"Transform"}],"nm":"Group 8","np":2,"cix":2,"bm":0,"ix":8,"mn":"ADBE Vector Group","hd":false}],"ip":0,"op":120,"st":0,"ct":1,"bm":0},{"ddd":0,"ind":4,"ty":4,"nm":"leg Outlines","sr":1,"ks":{"o":{"a":0,"k":100,"ix":11},"r":{"a":0,"k":0,"ix":10},"p":{"a":0,"k":[983.425,782.596,0],"ix":2,"l":2},"a":{"a":0,"k":[89.439,262.654,0],"ix":1,"l":2},"s":{"a":0,"k":[100,100,100],"ix":6,"l":2}},"ao":0,"shapes":[{"ty":"gr","it":[{"ind":0,"ty":"sh","ix":1,"ks":{"a":0,"k":{"i":[[18.601,-5.145],[2.208,-7.664],[0.019,-0.066],[0.017,-0.062],[-6.951,0],[0,0],[0.002,9.991],[4.06,-1.52],[4.94,-1.924],[6.386,12.772],[3.314,0.833],[-0.233,-5.073],[-0.038,-0.41],[3.998,-4.658]],"o":[[-6.811,1.885],[-0.019,0.065],[-0.018,0.062],[-1.837,6.704],[0,0],[9.991,0],[0.305,-11.253],[-4.06,1.517],[-10.926,4.258],[-2.423,-4.846],[-4.342,-1.09],[0.019,0.403],[0.57,6.111],[-6.572,7.655]],"v":[[-50.047,11.471],[-65.337,25.209],[-65.393,25.405],[-65.445,25.593],[-55.144,38.88],[48.891,38.88],[66.977,20.79],[46.036,-32.483],[37.231,-18.986],[9.914,-30.072],[0.219,-37.79],[-7.947,-29.792],[-7.861,-28.573],[-13.049,-11.716]],"c":true},"ix":2},"nm":"Path 1","mn":"ADBE Vector Shape - Group","hd":false},{"ty":"fl","c":{"a":0,"k":[0.807843197093,0.807843197093,0.807843197093,1],"ix":4},"o":{"a":0,"k":100,"ix":5},"r":1,"bm":0,"nm":"Fill 1","mn":"ADBE Vector Graphic - Fill","hd":false},{"ty":"tr","p":{"a":0,"k":[67.532,477.242],"ix":2},"a":{"a":0,"k":[0,0],"ix":1},"s":{"a":0,"k":[100,100],"ix":3},"r":{"a":0,"k":0,"ix":6},"o":{"a":0,"k":100,"ix":7},"sk":{"a":0,"k":0,"ix":4},"sa":{"a":0,"k":0,"ix":5},"nm":"Transform"}],"nm":"Group 1","np":2,"cix":2,"bm":0,"ix":1,"mn":"ADBE Vector Group","hd":false},{"ty":"gr","it":[{"ind":0,"ty":"sh","ix":1,"ks":{"a":0,"k":{"i":[[37.849,0],[0,0],[-2.914,-34.491],[0,0],[0,0],[-19.885,0],[-0.274,22.651],[0,0],[0,0]],"o":[[0,0],[-34.613,0],[0,0],[0,0],[0.276,22.651],[19.886,0],[0,0],[0,0],[8.252,-36.937]],"v":[[-2.063,-133.438],[-2.063,-133.438],[-60.972,-69.343],[-47.3,92.52],[-47.288,92.52],[-15.075,133.438],[21.229,92.52],[21.242,92.52],[55.634,-61.43]],"c":true},"ix":2},"nm":"Path 1","mn":"ADBE Vector Shape - Group","hd":false},{"ty":"fl","c":{"a":0,"k":[0,0,0,1],"ix":4},"o":{"a":0,"k":100,"ix":5},"r":1,"bm":0,"nm":"Fill 1","mn":"ADBE Vector Graphic - Fill","hd":false},{"ty":"tr","p":{"a":0,"k":[114.741,133.688],"ix":2},"a":{"a":0,"k":[0,0],"ix":1},"s":{"a":0,"k":[100,100],"ix":3},"r":{"a":0,"k":0,"ix":6},"o":{"a":0,"k":100,"ix":7},"sk":{"a":0,"k":0,"ix":4},"sa":{"a":0,"k":0,"ix":5},"nm":"Transform"}],"nm":"Group 2","np":2,"cix":2,"bm":0,"ix":2,"mn":"ADBE Vector Group","hd":false},{"ty":"gr","it":[{"ind":0,"ty":"sh","ix":1,"ks":{"a":0,"k":{"i":[[0,0],[0,0],[20.058,0],[0,-22.922],[-0.134,-1.451],[0,0]],"o":[[33.338,-95.098],[0,-22.922],[-20.057,0],[0,1.491],[0,0],[0,0]],"v":[[5.554,122.689],[29.65,-81.185],[-6.667,-122.689],[-38.891,-81.185],[-38.685,-76.77],[-31.74,122.525]],"c":true},"ix":2},"nm":"Path 1","mn":"ADBE Vector Shape - Group","hd":false},{"ty":"fl","c":{"a":0,"k":[0,0,0,1],"ix":4},"o":{"a":0,"k":100,"ix":5},"r":1,"bm":0,"nm":"Fill 1","mn":"ADBE Vector Graphic - Fill","hd":false},{"ty":"tr","p":{"a":0,"k":[107.868,305.858],"ix":2},"a":{"a":0,"k":[0,0],"ix":1},"s":{"a":0,"k":[100,100],"ix":3},"r":{"a":0,"k":0,"ix":6},"o":{"a":0,"k":100,"ix":7},"sk":{"a":0,"k":0,"ix":4},"sa":{"a":0,"k":0,"ix":5},"nm":"Transform"}],"nm":"Group 3","np":2,"cix":2,"bm":0,"ix":3,"mn":"ADBE Vector Group","hd":false},{"ty":"gr","it":[{"ind":0,"ty":"sh","ix":1,"ks":{"a":0,"k":{"i":[[0,0],[0,0],[0,0],[0,0]],"o":[[0,0],[0,0],[0,0],[0,0]],"v":[[-17.268,-43.573],[-19.561,40.388],[19.561,46.452],[19.561,-46.451]],"c":true},"ix":2},"nm":"Path 1","mn":"ADBE Vector Shape - Group","hd":false},{"ty":"fl","c":{"a":0,"k":[1,0.752941236309,0.701960784314,1],"ix":4},"o":{"a":0,"k":100,"ix":5},"r":1,"bm":0,"nm":"Fill 1","mn":"ADBE Vector Graphic - Fill","hd":false},{"ty":"tr","p":{"a":0,"k":[93.756,451.496],"ix":2},"a":{"a":0,"k":[0,0],"ix":1},"s":{"a":0,"k":[100,100],"ix":3},"r":{"a":0,"k":0,"ix":6},"o":{"a":0,"k":100,"ix":7},"sk":{"a":0,"k":0,"ix":4},"sa":{"a":0,"k":0,"ix":5},"nm":"Transform"}],"nm":"Group 4","np":2,"cix":2,"bm":0,"ix":4,"mn":"ADBE Vector Group","hd":false},{"ty":"gr","it":[{"ind":0,"ty":"sh","ix":1,"ks":{"a":0,"k":{"i":[[8.192,0],[0,0],[0,8.192],[-8.192,0],[0,0],[0,-12.787]],"o":[[0,0],[-8.192,0],[0,-8.192],[0,0],[11.765,0],[0,8.192]],"v":[[54.732,14.834],[-51.663,14.834],[-66.496,0],[-51.663,-14.834],[54.732,-14.834],[66.496,0]],"c":true},"ix":2},"nm":"Path 1","mn":"ADBE Vector Shape - Group","hd":false},{"ty":"fl","c":{"a":0,"k":[0.258823529412,0.258823529412,0.258823529412,1],"ix":4},"o":{"a":0,"k":100,"ix":5},"r":1,"bm":0,"nm":"Fill 1","mn":"ADBE Vector Graphic - Fill","hd":false},{"ty":"tr","p":{"a":0,"k":[67.266,510.224],"ix":2},"a":{"a":0,"k":[0,0],"ix":1},"s":{"a":0,"k":[100,100],"ix":3},"r":{"a":0,"k":0,"ix":6},"o":{"a":0,"k":100,"ix":7},"sk":{"a":0,"k":0,"ix":4},"sa":{"a":0,"k":0,"ix":5},"nm":"Transform"}],"nm":"Group 5","np":2,"cix":2,"bm":0,"ix":5,"mn":"ADBE Vector Group","hd":false},{"ty":"gr","it":[{"ind":0,"ty":"sh","ix":1,"ks":{"a":0,"k":{"i":[[16.933,-4.684],[2.01,-6.976],[0.017,-0.059],[0.016,-0.057],[-6.328,0],[0,0],[0.002,9.095],[3.696,-1.383],[4.496,-1.752],[5.815,11.627],[3.018,0.758],[-0.213,-4.618],[-0.035,-0.373],[3.64,-4.241]],"o":[[-6.2,1.716],[-0.017,0.059],[-0.016,0.057],[-1.672,6.102],[0,0],[9.094,0],[0.277,-10.243],[-3.695,1.382],[-9.948,3.876],[-2.205,-4.411],[-3.952,-0.993],[0.017,0.367],[0.519,5.563],[-5.982,6.967]],"v":[[-45.559,10.442],[-59.478,22.948],[-59.529,23.126],[-59.577,23.298],[-50.199,35.393],[44.508,35.393],[60.972,18.925],[41.908,-29.571],[33.894,-17.284],[9.024,-27.376],[0.199,-34.401],[-7.234,-27.121],[-7.156,-26.01],[-11.879,-10.665]],"c":true},"ix":2},"nm":"Path 1","mn":"ADBE Vector Shape - Group","hd":false},{"ty":"fl","c":{"a":0,"k":[0.807843197093,0.807843197093,0.807843197093,1],"ix":4},"o":{"a":0,"k":100,"ix":5},"r":1,"bm":0,"nm":"Fill 1","mn":"ADBE Vector Graphic - Fill","hd":false},{"ty":"tr","p":{"a":0,"k":[69.238,434.471],"ix":2},"a":{"a":0,"k":[0,0],"ix":1},"s":{"a":0,"k":[100,100],"ix":3},"r":{"a":0,"k":0,"ix":6},"o":{"a":0,"k":100,"ix":7},"sk":{"a":0,"k":0,"ix":4},"sa":{"a":0,"k":0,"ix":5},"nm":"Transform"}],"nm":"Group 6","np":2,"cix":2,"bm":0,"ix":6,"mn":"ADBE Vector Group","hd":false},{"ty":"gr","it":[{"ind":0,"ty":"sh","ix":1,"ks":{"a":0,"k":{"i":[[34.455,0],[0,0],[-2.652,-31.398],[0,0],[0,0],[-18.102,0],[-0.25,20.62],[0,0],[0,0]],"o":[[0,0],[-31.51,0],[0,0],[0,0],[0.25,20.62],[18.103,0],[0,0],[0,0],[7.512,-33.626]],"v":[[-1.878,-121.473],[-1.878,-121.473],[-55.505,-63.125],[-43.059,84.223],[-43.047,84.223],[-13.724,121.473],[19.325,84.223],[19.337,84.223],[50.645,-55.922]],"c":true},"ix":2},"nm":"Path 1","mn":"ADBE Vector Shape - Group","hd":false},{"ty":"fl","c":{"a":0,"k":[0,0,0,1],"ix":4},"o":{"a":0,"k":100,"ix":5},"r":1,"bm":0,"nm":"Fill 1","mn":"ADBE Vector Graphic - Fill","hd":false},{"ty":"tr","p":{"a":0,"k":[112.214,121.723],"ix":2},"a":{"a":0,"k":[0,0],"ix":1},"s":{"a":0,"k":[100,100],"ix":3},"r":{"a":0,"k":0,"ix":6},"o":{"a":0,"k":100,"ix":7},"sk":{"a":0,"k":0,"ix":4},"sa":{"a":0,"k":0,"ix":5},"nm":"Transform"}],"nm":"Group 7","np":2,"cix":2,"bm":0,"ix":7,"mn":"ADBE Vector Group","hd":false},{"ty":"gr","it":[{"ind":0,"ty":"sh","ix":1,"ks":{"a":0,"k":{"i":[[0,0],[0,0],[18.259,0],[0,-20.866],[-0.123,-1.322],[0,0]],"o":[[30.349,-86.57],[0,-20.866],[-18.259,0],[0,1.359],[0,0],[0,0]],"v":[[5.056,111.688],[26.992,-73.906],[-6.069,-111.687],[-35.404,-73.906],[-35.216,-69.886],[-28.894,111.539]],"c":true},"ix":2},"nm":"Path 1","mn":"ADBE Vector Shape - Group","hd":false},{"ty":"fl","c":{"a":0,"k":[0,0,0,1],"ix":4},"o":{"a":0,"k":100,"ix":5},"r":1,"bm":0,"nm":"Fill 1","mn":"ADBE Vector Graphic - Fill","hd":false},{"ty":"tr","p":{"a":0,"k":[104.56,279.852],"ix":2},"a":{"a":0,"k":[0,0],"ix":1},"s":{"a":0,"k":[100,100],"ix":3},"r":{"a":0,"k":0,"ix":6},"o":{"a":0,"k":100,"ix":7},"sk":{"a":0,"k":0,"ix":4},"sa":{"a":0,"k":0,"ix":5},"nm":"Transform"}],"nm":"Group 8","np":2,"cix":2,"bm":0,"ix":8,"mn":"ADBE Vector Group","hd":false},{"ty":"gr","it":[{"ind":0,"ty":"sh","ix":1,"ks":{"a":0,"k":{"i":[[0,0],[0,0],[0,0],[0,0]],"o":[[0,0],[0,0],[0,0],[0,0]],"v":[[-15.719,-39.667],[-17.807,36.765],[17.807,42.286],[17.807,-42.286]],"c":true},"ix":2},"nm":"Path 1","mn":"ADBE Vector Shape - Group","hd":false},{"ty":"fl","c":{"a":0,"k":[1,0.752941236309,0.701960784314,1],"ix":4},"o":{"a":0,"k":100,"ix":5},"r":1,"bm":0,"nm":"Fill 1","mn":"ADBE Vector Graphic - Fill","hd":false},{"ty":"tr","p":{"a":0,"k":[91.713,412.431],"ix":2},"a":{"a":0,"k":[0,0],"ix":1},"s":{"a":0,"k":[100,100],"ix":3},"r":{"a":0,"k":0,"ix":6},"o":{"a":0,"k":100,"ix":7},"sk":{"a":0,"k":0,"ix":4},"sa":{"a":0,"k":0,"ix":5},"nm":"Transform"}],"nm":"Group 9","np":2,"cix":2,"bm":0,"ix":9,"mn":"ADBE Vector Group","hd":false},{"ty":"gr","it":[{"ind":0,"ty":"sh","ix":1,"ks":{"a":0,"k":{"i":[[7.457,0],[0,0],[0,7.458],[-7.458,0],[0,0],[0,-11.641]],"o":[[0,0],[-7.458,0],[0,-7.458],[0,0],[10.709,0],[0,7.458]],"v":[[49.825,13.504],[-47.029,13.504],[-60.534,0],[-47.029,-13.504],[49.825,-13.504],[60.534,0]],"c":true},"ix":2},"nm":"Path 1","mn":"ADBE Vector Shape - Group","hd":false},{"ty":"fl","c":{"a":0,"k":[0.258823529412,0.258823529412,0.258823529412,1],"ix":4},"o":{"a":0,"k":100,"ix":5},"r":1,"bm":0,"nm":"Fill 1","mn":"ADBE Vector Graphic - Fill","hd":false},{"ty":"tr","p":{"a":0,"k":[69.475,464.496],"ix":2},"a":{"a":0,"k":[0,0],"ix":1},"s":{"a":0,"k":[100,100],"ix":3},"r":{"a":0,"k":0,"ix":6},"o":{"a":0,"k":100,"ix":7},"sk":{"a":0,"k":0,"ix":4},"sa":{"a":0,"k":0,"ix":5},"nm":"Transform"}],"nm":"Group 10","np":2,"cix":2,"bm":0,"ix":10,"mn":"ADBE Vector Group","hd":false}],"ip":0,"op":120,"st":0,"ct":1,"bm":0},{"ddd":0,"ind":5,"ty":4,"nm":"hand l Outlines 2","parent":6,"sr":1,"ks":{"o":{"a":0,"k":100,"ix":11},"r":{"a":1,"k":[{"i":{"x":[0.353],"y":[1]},"o":{"x":[0.333],"y":[0]},"t":60,"s":[-28]},{"i":{"x":[0.667],"y":[1]},"o":{"x":[0.653],"y":[0]},"t":90,"s":[-22]},{"t":120,"s":[-28]}],"ix":10},"p":{"a":0,"k":[25.607,163.752,0],"ix":2,"l":2},"a":{"a":0,"k":[182.997,24.588,0],"ix":1,"l":2},"s":{"a":0,"k":[100,100,100],"ix":6,"l":2}},"ao":0,"shapes":[{"ty":"gr","it":[{"ind":0,"ty":"sh","ix":1,"ks":{"a":0,"k":{"i":[[-2.082,6.375],[6.375,2.082],[2.082,-6.375],[-6.374,-2.082]],"o":[[2.083,-6.375],[-6.375,-2.083],[-2.082,6.375],[6.375,2.083]],"v":[[11.542,3.77],[3.77,-11.543],[-11.543,-3.77],[-3.771,11.543]],"c":true},"ix":2},"nm":"Path 1","mn":"ADBE Vector Shape - Group","hd":false},{"ty":"fl","c":{"a":0,"k":[0.800000059838,0.800000059838,0.800000059838,1],"ix":4},"o":{"a":0,"k":100,"ix":5},"r":1,"bm":0,"nm":"Fill 1","mn":"ADBE Vector Graphic - Fill","hd":false},{"ty":"tr","p":{"a":0,"k":[80.198,144.979],"ix":2},"a":{"a":0,"k":[0,0],"ix":1},"s":{"a":0,"k":[100,100],"ix":3},"r":{"a":0,"k":0,"ix":6},"o":{"a":0,"k":100,"ix":7},"sk":{"a":0,"k":0,"ix":4},"sa":{"a":0,"k":0,"ix":5},"nm":"Transform"}],"nm":"Group 1","np":2,"cix":2,"bm":0,"ix":1,"mn":"ADBE Vector Group","hd":false},{"ty":"gr","it":[{"ind":0,"ty":"sh","ix":1,"ks":{"a":0,"k":{"i":[[-3.527,10.797],[10.798,3.527],[3.527,-10.797],[-10.797,-3.527]],"o":[[3.527,-10.798],[-10.797,-3.526],[-3.526,10.798],[10.798,3.526]],"v":[[19.551,6.386],[6.385,-19.551],[-19.552,-6.386],[-6.386,19.551]],"c":true},"ix":2},"nm":"Path 1","mn":"ADBE Vector Shape - Group","hd":false},{"ty":"fl","c":{"a":0,"k":[0.686274509804,0.686274509804,0.686274509804,1],"ix":4},"o":{"a":0,"k":100,"ix":5},"r":1,"bm":0,"nm":"Fill 1","mn":"ADBE Vector Graphic - Fill","hd":false},{"ty":"tr","p":{"a":0,"k":[80.198,144.979],"ix":2},"a":{"a":0,"k":[0,0],"ix":1},"s":{"a":0,"k":[100,100],"ix":3},"r":{"a":0,"k":0,"ix":6},"o":{"a":0,"k":100,"ix":7},"sk":{"a":0,"k":0,"ix":4},"sa":{"a":0,"k":0,"ix":5},"nm":"Transform"}],"nm":"Group 2","np":2,"cix":2,"bm":0,"ix":2,"mn":"ADBE Vector Group","hd":false},{"ty":"gr","it":[{"ind":0,"ty":"sh","ix":1,"ks":{"a":0,"k":{"i":[[-10.329,31.621],[31.621,10.329],[10.329,-31.621],[-31.621,-10.329]],"o":[[10.328,-31.622],[-31.622,-10.329],[-10.328,31.622],[31.622,10.328]],"v":[[57.256,18.701],[18.702,-57.256],[-57.256,-18.701],[-18.702,57.256]],"c":true},"ix":2},"nm":"Path 1","mn":"ADBE Vector Shape - Group","hd":false},{"ty":"fl","c":{"a":0,"k":[0.427450980392,0.427450980392,0.427450980392,1],"ix":4},"o":{"a":0,"k":100,"ix":5},"r":1,"bm":0,"nm":"Fill 1","mn":"ADBE Vector Graphic - Fill","hd":false},{"ty":"tr","p":{"a":0,"k":[80.197,144.979],"ix":2},"a":{"a":0,"k":[0,0],"ix":1},"s":{"a":0,"k":[100,100],"ix":3},"r":{"a":0,"k":0,"ix":6},"o":{"a":0,"k":100,"ix":7},"sk":{"a":0,"k":0,"ix":4},"sa":{"a":0,"k":0,"ix":5},"nm":"Transform"}],"nm":"Group 3","np":2,"cix":2,"bm":0,"ix":3,"mn":"ADBE Vector Group","hd":false},{"ty":"gr","it":[{"ind":0,"ty":"sh","ix":1,"ks":{"a":0,"k":{"i":[[-12.218,37.406],[37.406,12.218],[12.218,-37.406],[-37.406,-12.218]],"o":[[12.218,-37.406],[-37.406,-12.217],[-12.218,37.406],[37.406,12.218]],"v":[[67.73,22.122],[22.122,-67.73],[-67.73,-22.123],[-22.123,67.729]],"c":true},"ix":2},"nm":"Path 1","mn":"ADBE Vector Shape - Group","hd":false},{"ty":"fl","c":{"a":0,"k":[0.61568627451,0.61568627451,0.61568627451,1],"ix":4},"o":{"a":0,"k":100,"ix":5},"r":1,"bm":0,"nm":"Fill 1","mn":"ADBE Vector Graphic - Fill","hd":false},{"ty":"tr","p":{"a":0,"k":[80.197,144.98],"ix":2},"a":{"a":0,"k":[0,0],"ix":1},"s":{"a":0,"k":[100,100],"ix":3},"r":{"a":0,"k":0,"ix":6},"o":{"a":0,"k":100,"ix":7},"sk":{"a":0,"k":0,"ix":4},"sa":{"a":0,"k":0,"ix":5},"nm":"Transform"}],"nm":"Group 4","np":2,"cix":2,"bm":0,"ix":4,"mn":"ADBE Vector Group","hd":false},{"ty":"gr","it":[{"ind":0,"ty":"sh","ix":1,"ks":{"a":0,"k":{"i":[[8.573,-9.682],[0,0],[8.161,7.788],[-6.24,8.061],[0,0],[-10.055,-8.981]],"o":[[0,0],[-7.478,8.446],[-7.375,-7.038],[0,0],[8.411,-10.536],[9.644,8.615]],"v":[[50.163,-24.134],[-21.863,57.21],[-50.499,58.414],[-52.496,31.841],[14.223,-54.357],[48.224,-57.221]],"c":true},"ix":2},"nm":"Path 1","mn":"ADBE Vector Shape - Group","hd":false},{"ty":"fl","c":{"a":0,"k":[0.329411764706,0.552941176471,0.776470648074,1],"ix":4},"o":{"a":0,"k":100,"ix":5},"r":1,"bm":0,"nm":"Fill 1","mn":"ADBE Vector Graphic - Fill","hd":false},{"ty":"tr","p":{"a":0,"k":[149.009,66.452],"ix":2},"a":{"a":0,"k":[0,0],"ix":1},"s":{"a":0,"k":[100,100],"ix":3},"r":{"a":0,"k":0,"ix":6},"o":{"a":0,"k":100,"ix":7},"sk":{"a":0,"k":0,"ix":4},"sa":{"a":0,"k":0,"ix":5},"nm":"Transform"}],"nm":"Group 5","np":2,"cix":2,"bm":0,"ix":5,"mn":"ADBE Vector Group","hd":false}],"ip":0,"op":120,"st":0,"ct":1,"bm":0},{"ddd":0,"ind":6,"ty":4,"nm":"hand u Outlines 2","sr":1,"ks":{"o":{"a":0,"k":100,"ix":11},"r":{"a":1,"k":[{"i":{"x":[0.353],"y":[1]},"o":{"x":[0.333],"y":[0]},"t":60,"s":[-12]},{"i":{"x":[0.667],"y":[1]},"o":{"x":[0.653],"y":[0]},"t":90,"s":[75]},{"t":120,"s":[-12]}],"ix":10},"p":{"a":0,"k":[1030.484,256.86,0],"ix":2,"l":2},"a":{"a":0,"k":[60.884,22.834,0],"ix":1,"l":2},"s":{"a":0,"k":[100,100,100],"ix":6,"l":2}},"ao":0,"shapes":[{"ty":"gr","it":[{"ind":0,"ty":"sh","ix":1,"ks":{"a":0,"k":{"i":[[3.75,-16.604],[0,0],[-11.853,-3.481],[-3.868,12.456],[0,0],[-0.244,1.64],[24.162,6.097]],"o":[[0,0],[-2.398,12.118],[12.514,3.675],[0,0],[0.509,-1.578],[1.41,-9.501],[-16.505,-4.164]],"v":[[-16.389,-67.195],[-42.236,63.363],[-25.542,90.909],[3.988,75.081],[39.497,-39.262],[40.634,-44.093],[20.473,-90.42]],"c":true},"ix":2},"nm":"Path 1","mn":"ADBE Vector Shape - Group","hd":false},{"ty":"fl","c":{"a":0,"k":[0.329411764706,0.552941176471,0.776470648074,1],"ix":4},"o":{"a":0,"k":100,"ix":5},"r":1,"bm":0,"nm":"Fill 1","mn":"ADBE Vector Graphic - Fill","hd":false},{"ty":"tr","p":{"a":0,"k":[44.884,94.834],"ix":2},"a":{"a":0,"k":[0,0],"ix":1},"s":{"a":0,"k":[100,100],"ix":3},"r":{"a":0,"k":0,"ix":6},"o":{"a":0,"k":100,"ix":7},"sk":{"a":0,"k":0,"ix":4},"sa":{"a":0,"k":0,"ix":5},"nm":"Transform"}],"nm":"Group 1","np":2,"cix":2,"bm":0,"ix":1,"mn":"ADBE Vector Group","hd":false}],"ip":0,"op":120,"st":0,"ct":1,"bm":0}],"markers":[]}